{
  "state": "Bihar",
  "district": "Aurangabad",
  "date": "2026-04-26",
  "article_count": 1,
  "articles": [
    {
      "title": "Heatwave Grips Bihar As Temperatures Near 44°C; Storms Likely In Northern Districts - Patna Press",
      "url": "https://news.google.com/rss/articles/CBMifkFVX3lxTE1acDRoWG52YWJjZ0RQbUROQ24xRDF3eE9XUEFuU1puRXlJZHhvQXo4UTVkdHpjdjlUSGpMUGExUUtZRXJ0MjBKUVBjTUh0MVdnbjV2allsemxlUjU3MGttb1ZQQmFMR0Z3akNaTTFxZGZ2Vy16REsxa3c3UkNoUQ?oc=5",
      "source": "Patna Press",
      "date": "2026-04-26T08:54:39+05:30",
      "language": "en",
      "state": "Bihar",
      "district": "Aurangabad",
      "search_term": "(heatwave OR \"heat wave\" OR \"severe heatwave\" OR \"extreme heat\" OR \"heat spell\" OR \"scorching heat\" OR \"blistering heat\" OR \"sweltering heat\" OR \"hot winds\" OR loo OR \"hot loo winds\" OR \"intense heat\" OR \"unbearable heat\" OR \"deadly heat\" OR heat OR \"weather forecast\" OR \"weather update\" OR \"weather alert\" OR \"IMD forecast\" OR \"IMD prediction\" OR \"IMD alert\" OR IMD OR \"rising temperatures\" OR \"temperatures expected to rise\" OR \"relief from heat\" OR \"respite from heat\" OR \"heat respite\" OR \"respite from scorching heat\") Bihar",
      "full_text": "Patna: Large parts of Bihar are reeling under intense heatwave conditions, with the Meteorological Department warning that high temperatures will persist across more than a dozen districts until Monday.\nDaytime temperatures are expected to range between 40°C and 44°C in several districts, including Patna, Gaya, Saran, Muzaffarpur, Buxar and Aurangabad, forcing many residents indoors during peak afternoon hours.\nHeatwave Conditions Persist\nOfficials said strong, dust-laden winds may sweep through isolated areas during the afternoon and evening, adding to discomfort in already affected regions.\nThe ongoing heatwave is expected to particularly impact southern and central parts of the state, where temperatures have remained significantly above normal.\nThunderstorm Alert In Northern Districts\nAt the same time, the India Meteorological Department (IMD) has issued an orange alert for thunderstorms, lightning and rainfall across several districts in north and east Bihar.\nDistricts including Darbhanga, Sitamarhi, Madhubani, Purnia and Bhagalpur are likely to experience thunderstorms accompanied by lightning and wind speeds of up to 50 kmph.\n‘Kal Baisakhi’ Conditions Developing\nMeteorologists said conditions are favourable for the development of Kal Baisakhi (Nor’westers) due to moisture incursion from the Bay of Bengal.\nThis could trigger dust storms, gusty winds and intermittent rainfall across several parts of the state over the next four to five days.\nLight rainfall has already been reported in areas such as Raxaul, while cloud cover has increased in regions like Bettiah.\nIn Patna, a change in weather is expected from Monday, with the possibility of light rain and strong winds bringing some relief from the heat.\nTwo Contrasting Weather Patterns\nOfficials said Bihar is likely to witness two distinct weather patterns in the coming days—continued heatwave conditions in the south and central regions, and relatively cooler, rain-affected conditions in the north and east.\nResidents have been advised to take precautions against heat exposure, while also remaining alert to thunderstorms and lightning activity.",
      "relevance_score": 1.0
    }
  ]
}