{
  "state": "West Bengal",
  "district": "Kolkata",
  "date": "2026-05-29",
  "article_count": 1,
  "articles": [
    {
      "title": "অবশেষে বৃষ্টি এল ঝেঁপে, তীব্র গরম ও অস্বস্তিকর আবহাওয়া উড়িয়ে স্বস্তির ছোঁয়া বাংলায় - Najarbandi",
      "url": "https://news.google.com/rss/articles/CBMidEFVX3lxTFBCQW40X1BQMDFQMjM1UldyTEFZdkExXzl0QkNmbFk2WHQtcmdZQUVMSktmTW5rYWZGWmVlcS1vYVZFS2l4TUFYT0lxVWZ4ZG9vcjYySkFTeDRldDlzUzcyOEU4VUhhUzI1OG9IZUJBTGJpWkI0?oc=5",
      "source": "Najarbandi",
      "date": "2026-05-29T14:41:48+05:30",
      "language": "bn",
      "state": "West Bengal",
      "district": "Kolkata",
      "search_term": "(দাবদাহ OR তাপপ্রবাহ OR \"প্রচণ্ড গরম\" OR \"তীব্র গরম\" OR \"ঝলসানো গরম\" OR \"লু হাওয়া\" OR \"গরমের দাপট\" OR দাবানল OR \"অসহ্য গরম\" OR \"হিট ওয়েভ\" OR \"অত্যধিক গরম\" OR \"ভয়াবহ গরম\") West Bengal",
      "full_text": "দিনভর তীব্র গরম ও অস্বস্তিকর আবহাওয়ার পর অবশেষে স্বস্তির বৃষ্টি। আবহাওয়ার খবর মিলিয়ে শুক্রবার বিকেল থেকে কলকাতা-সহ দক্ষিণবঙ্গের একাধিক জেলায় বজ্রবিদ্যুৎ-সহ ঝড়বৃষ্টি শুরু হয়েছে। আবহাওয়া দফতরের পূর্বাভাসের সঙ্গে মিল রেখে রাজ্যের বিভিন্ন প্রান্তে দেখা দিয়েছে কালো মেঘ, দমকা হাওয়া এবং বৃষ্টির দাপট। একই সঙ্গে বঙ্গোপসাগরে প্রতিকূল আবহাওয়ার জেরে মৎস্যজীবীদের জন্য জারি হয়েছে বিশেষ সতর্কতা।\nআলিপুর আবহাওয়া দফতর জানিয়েছে, দক্ষিণবঙ্গে বিকেলের পর থেকেই আবহাওয়ার দ্রুত পরিবর্তন হওয়ার সম্ভাবনা ছিল। সেই পূর্বাভাস বাস্তবে রূপ নিয়ে কলকাতা ও আশপাশের জেলাগুলিতে বজ্রবিদ্যুৎ-সহ বৃষ্টি শুরু হয়েছে। কোথাও কোথাও ঝড়ের গতিবেগ ঘণ্টায় ৬০ থেকে ৭০ কিলোমিটার পর্যন্ত পৌঁছতে পারে বলেও সতর্ক করা হয়েছে।\nবিশেষভাবে নজরে রয়েছে পূর্ব মেদিনীপুর, পশ্চিম মেদিনীপুর, ঝাড়গ্রাম, পূর্ব বর্ধমান, পশ্চিম বর্ধমান, বাঁকুড়া এবং পুরুলিয়া। আবহাওয়া দফতরের মতে, এই জেলাগুলিতে ঝড়বৃষ্টির তীব্রতা তুলনামূলক বেশি হতে পারে। পাশাপাশি বজ্রপাতের ঝুঁকিও থাকায় বাসিন্দাদের সতর্ক থাকার পরামর্শ দেওয়া হয়েছে।\nআবহাওয়াবিদরা জানিয়েছেন, ঝাড়খণ্ড সংলগ্ন এলাকায় সক্রিয় ঘূর্ণাবর্ত এবং উত্তরপ্রদেশ থেকে অন্ধ্রপ্রদেশ পর্যন্ত বিস্তৃত অক্ষরেখার প্রভাবেই এই আবহাওয়ার পরিবর্তন ঘটছে। এর সঙ্গে দক্ষিণ-পশ্চিম মৌসুমী বায়ুও ধীরে ধীরে মধ্য ও উত্তর বঙ্গোপসাগরের দিকে অগ্রসর হওয়ায় বৃষ্টির অনুকূল পরিবেশ তৈরি হয়েছে।\nএদিকে সমুদ্র পরিস্থিতি নিয়েও উদ্বেগ রয়েছে। বাংলা ও উত্তর ওড়িশা উপকূল সংলগ্ন বঙ্গোপসাগরে সমুদ্র উত্তাল হওয়ার আশঙ্কা প্রকাশ করেছে আবহাওয়া দফতর। সমুদ্রপৃষ্ঠের উপরের স্তরে ঘণ্টায় ৬০ কিলোমিটার বা তার বেশি গতিতে বায়ুপ্রবাহ তৈরি হতে পারে। সেই কারণেই আগামী ২৪ ঘণ্টার জন্য মৎস্যজীবীদের সমুদ্রে না যাওয়ার পরামর্শ দেওয়া হয়েছে।\nশনিবারও দক্ষিণবঙ্গের কয়েকটি জেলায় বিক্ষিপ্তভাবে ঝড়বৃষ্টি অব্যাহত থাকতে পারে। তবে রবিবার থেকে পরিস্থিতির কিছুটা উন্নতি হওয়ার সম্ভাবনা রয়েছে। ধীরে ধীরে ঝড়ের তীব্রতা কমবে এবং বৃষ্টির পরিমাণও হ্রাস পাবে বলে পূর্বাভাস।\nউত্তরবঙ্গেও আবহাওয়ার প্রভাব দেখা যেতে পারে। মালদহ, উত্তর দিনাজপুর ও দক্ষিণ দিনাজপুরে ঘণ্টায় ৪০ থেকে ৫০ কিলোমিটার বেগে ঝড়ের সঙ্গে ভারী বৃষ্টির সম্ভাবনা রয়েছে। শনিবার প্রায় সব জেলাতেই বিক্ষিপ্ত বৃষ্টি হতে পারে, যদিও রবিবারের পর থেকে ঝড়বৃষ্টির প্রবণতা কমার ইঙ্গিত মিলেছে।\nতবে এই স্বস্তি দীর্ঘস্থায়ী নাও হতে পারে। আবহাওয়া দফতরের পূর্বাভাস অনুযায়ী, জুন মাসের প্রথম সপ্তাহ থেকেই আবারও তাপমাত্রা বাড়তে পারে এবং দক্ষিণবঙ্গের একাধিক এলাকায় দাবদাহ পরিস্থিতি ফিরে আসার আশঙ্কা রয়েছে। ফলে আপাতত বৃষ্টি ও ঝড় কিছুটা স্বস্তি দিলেও গরমের দাপট থেকে স্থায়ী মুক্তি এখনও অনেক দূরের পথ।\nসবচেয়ে আগে সঠিক খবর, প্রতি মুহূর্তে\nGoogle News এবং Google Discover-এ নজরবন্দি-কে Follow করে রাখুন।",
      "relevance_score": 1.0
    }
  ]
}