{
  "state": "Madhya Pradesh",
  "district": null,
  "date": "2026-03-31",
  "article_count": 2,
  "articles": [
    {
      "title": "आज का मौसम, 31 मार्च: उत्तर से दक्षिण तक तेज धूप रहेगी। - Vietnam.vn",
      "url": "https://news.google.com/rss/articles/CBMiggFBVV95cUxNa1dDZGxnVng1WWZUVFE3WlhhX3ZBWllqSHhNSGt3dnhZWGIzWXhMcUthR2QwNW9kRWtITnZxREgtU0podVNGY3VsTmhFT2pxa1Q3N2tySlRlb2NEdUxGUmpPaTlnbG9fQWxIYS1DWkNrcFZNYWJRZFg3M3Izc0lXczh3?oc=5",
      "source": "Vietnam.vn",
      "date": "2026-03-31T04:50:56+05:30",
      "language": "hi",
      "state": "Madhya Pradesh",
      "district": null,
      "search_term": "(लू OR \"लू चलना\" OR \"भीषण गर्मी\" OR \"प्रचंड गर्मी\" OR \"कड़ी धूप\" OR \"तेज धूप\" OR \"गर्म हवा\" OR \"उष्ण लहर\" OR \"ताप लहर\" OR \"हीट वेव\" OR \"झुलसाने वाली गर्मी\" OR \"तपती गर्मी\" OR \"भयंकर गर्मी\" OR \"गर्मी का कहर\" OR \"गर्मी का प्रकोप\" OR \"अत्यधिक गर्मी\" OR मौसम OR \"मौसम अपडेट\" OR \"मौसम का हाल\" OR \"मौसम पूर्वानुमान\" OR \"मौसम अलर्ट\" OR आईएमडी OR \"आईएमडी पूर्वानुमान\" OR \"आईएमडी अलर्ट\" OR \"तापमान में बढ़ोतरी\" OR \"गर्मी से राहत\" OR \"गर्मी से निजात\") Madhya Pradesh",
      "full_text": "आज, 31 मार्च को, पूरे देश में गर्म मौसम छाया हुआ है, उमस भरी स्थिति है और कुछ क्षेत्रों में तापमान 37-38 डिग्री सेल्सियस तक पहुंच गया है।\nराष्ट्रीय जल-मौसम विज्ञान पूर्वानुमान केंद्र के अनुसार, आज, 31 मार्च को, उत्तर-पश्चिमी क्षेत्र और थान्ह होआ से क्वांग न्गाई तक का मौसम गर्म और धूप वाला रहेगा, जिसमें न्घे आन से ह्यू शहर तक के पश्चिमी पहाड़ी क्षेत्रों में विशेष रूप से तीव्र गर्मी होगी।\nतापमान आमतौर पर 35-37 डिग्री सेल्सियस रहता है, जबकि पश्चिम में न्घे आन से ह्यू शहर तक फैले पहाड़ी क्षेत्रों में तापमान 36-38 डिग्री सेल्सियस तक पहुंच जाता है, और कुछ स्थानों पर यह 38 डिग्री सेल्सियस से भी अधिक हो जाता है। आर्द्रता कम से कम 45-55% रहती है।\nउत्तरी डेल्टा क्षेत्र में भीषण गर्मी पड़ रही है, तापमान 35-36 डिग्री सेल्सियस तक पहुंच गया है, और कुछ क्षेत्रों में तो यह 36 डिग्री सेल्सियस से भी अधिक हो गया है, जबकि आर्द्रता 60-65% के अपने न्यूनतम स्तर पर है।\n1 से 4 अप्रैल तक इन क्षेत्रों में लू की लहर धीरे-धीरे कम हो जाएगी।\nवियतनाम के दक्षिणपूर्वी क्षेत्र में भीषण गर्मी जारी है, जहां तापमान 35-36 डिग्री सेल्सियस तक पहुंच गया है और कुछ क्षेत्रों में तो यह 36 डिग्री सेल्सियस से भी अधिक हो गया है। आर्द्रता 45-50% के बीच बनी हुई है।\nकंक्रीट या डामर जैसी सतहों की स्थिति के आधार पर, वास्तविक बाहरी तापमान पूर्वानुमान से 2-4 डिग्री सेल्सियस या उससे अधिक हो सकता है।\nवास्तव में, शहरी क्षेत्रों में सड़कों और इमारतों के प्रभाव के कारण सूर्य की गर्मी काफी तीव्र होती है। लोगों को अनुमान से कहीं अधिक गर्मी महसूस होती है। इमारतें हवा को रोकती हैं, जिससे वातावरण और भी उमस भरा हो जाता है।\nआज, 31 मार्च के लिए विस्तृत मौसम पूर्वानुमान:\nहनोई में दिन के समय बादल छाए रहेंगे और तेज धूप निकलेगी। न्यूनतम तापमान 23-25 डिग्री सेल्सियस और अधिकतम तापमान 34-36 डिग्री सेल्सियस रहेगा।\nउत्तर-पश्चिमी क्षेत्र में दिन के समय बादल छाए रहेंगे और तेज धूप निकलेगी। न्यूनतम तापमान 19-25 डिग्री सेल्सियस और अधिकतम तापमान 34-37 डिग्री सेल्सियस रहेगा।\nपूर्वोत्तर क्षेत्र में बादल छाए रहेंगे और बीच-बीच में धूप भी निकलेगी। कुछ इलाकों में गर्मी भी रहेगी। न्यूनतम तापमान 23-26 डिग्री सेल्सियस और अधिकतम तापमान 31-36 डिग्री सेल्सियस रहेगा।\nथान्ह होआ से ह्यू तक , विशेषकर न्घे आन से ह्यू तक के पश्चिमी पहाड़ी क्षेत्रों में, बादल छाए रहेंगे और भीषण गर्मी पड़ेगी। न्यूनतम तापमान 24-27 डिग्री सेल्सियस और अधिकतम तापमान 35-38 डिग्री सेल्सियस रहेगा।\nदक्षिण मध्य तटीय क्षेत्र में बादल छाए रहेंगे और बीच-बीच में धूप भी निकलेगी। कुछ क्षेत्रों में गर्मी भी रहेगी। न्यूनतम तापमान 22-25 डिग्री सेल्सियस और अधिकतम तापमान 31-35 डिग्री सेल्सियस रहेगा।\nमध्य पर्वतीय क्षेत्र में बादल छाए रहेंगे और कुछ दिनों धूप भी निकलेगी। कुछ क्षेत्रों में गर्मी भी रहेगी। न्यूनतम तापमान 18-21 डिग्री सेल्सियस और अधिकतम तापमान 31-35 डिग्री सेल्सियस रहेगा।\nदक्षिणी वियतनाम में बादल छाए रहेंगे और बीच-बीच में धूप भी निकलेगी। कुछ इलाकों में गर्मी भी रहेगी। न्यूनतम तापमान 22-25 डिग्री सेल्सियस और अधिकतम तापमान 34-36 डिग्री सेल्सियस रहेगा।\nहो ची मिन्ह सिटी में बादल छाए रहेंगे और बीच-बीच में धूप भी निकलेगी। न्यूनतम तापमान 24-26 डिग्री सेल्सियस और अधिकतम तापमान 33-35 डिग्री सेल्सियस रहेगा।\ntuoitre.vn के अनुसार\nस्रोत: https://baovinhlong.com.vn/thoi-su/202603/thoi-tiet-hom-nay-313-nang-gay-gat-tu-bac-toi-nam-6812640/",
      "relevance_score": 1.0
    },
    {
      "title": "Penang JPN Enhances Preparedness Of 398 Schools To Face Heat Wave - Bernama",
      "url": "https://news.google.com/rss/articles/CBMiYkFVX3lxTE5Ibm5lQnZMZXdDVkFMbEVxSEVfTGNCUm1YdkxYYm9RTHE5Um9ocE4xQzVhYU13YXNRRk00RzUwNGlLN0IyOGRUWmk1a0FkM0ROVzNoTS1OTVMtWXVpR3lGZ05n?oc=5",
      "source": "Bernama",
      "date": "2026-03-31T04:36:29+05:30",
      "language": "en",
      "state": "Madhya Pradesh",
      "district": null,
      "search_term": "(heatwave OR \"heat wave\" OR \"severe heatwave\" OR \"extreme heat\" OR \"heat spell\" OR \"scorching heat\" OR \"blistering heat\" OR \"sweltering heat\" OR \"hot winds\" OR loo OR \"hot loo winds\" OR \"intense heat\" OR \"unbearable heat\" OR \"deadly heat\" OR heat OR \"weather forecast\" OR \"weather update\" OR \"weather alert\" OR \"IMD forecast\" OR \"IMD prediction\" OR \"IMD alert\" OR IMD OR \"rising temperatures\" OR \"temperatures expected to rise\" OR \"relief from heat\" OR \"respite from heat\" OR \"heat respite\" OR \"respite from scorching heat\") Madhya Pradesh",
      "full_text": "GEORGE TOWN, March 30 (Bernama) -- The Penang State Education Department (JPN) is taking proactive steps by strengthening the preparedness of schools throughout the state in the face of the current heat wave.\nState Education director Mohamad Dziauddin Mat Saad said this included holding an engagement session with all headmasters, principals and the District Education Office (PPD) to ensure that all 398 schools make preparations before the school session reopens, based on guidelines issued by the Ministry of Education (MOE).\nHe said that as a result of the engagement last Friday, schools had taken immediate action by informing parents in advance about the adjustment of schedules and students' needs during the hot weather period, including giving schools autonomy to determine more comfortable clothing.\n“Parents have also been informed about this preparation to give confidence that the school will ensure that the three main things, namely the health, welfare and safety of students, are always taken care of.\n“That is why we can see that on the first day of school opening today, children came wearing T-shirts, carrying water supplies, mini fans and the school even took the initiative to provide water supplies in the canteen,” he told reporters after conducting a survey at Sekolah Kebangsaan (SK) Sungai Gelugor here today.\nCommenting further, Mohamad Dziauddin said JPN was also paying attention to the school infrastructure aspects, especially involving fans, windows and ventilation systems to ensure that the learning environment remains conducive.\nIn this regard, he said the Infrastructure and Procurement Sector had been instructed to immediately review any issues related to the facilities so that repair work could be carried out immediately.\nHe also said that outdoor activities such as sports and co-curricular activities could still continue with certain adjustments, including being carried out in covered areas or early in the morning to avoid exposure to hot weather.\nAlthough Penang is not in the level on the current situation, Mohamad Dziauddin said that monitoring is being carried out continuously and his party is always in close contact with the Malaysian Meteorological Department (MetMalaysia) to obtain the latest weather information to be distributed to schools.\nHe informed that so far, there is no need to implement Teaching and Learning at Home (PdPR) and school sessions will continue to be held face-to-face.\nIn addition, he said that as part of the educational approach, schools are also encouraged to perform the Istisqa’ sunnah prayer to pray for rain.\n-- BERNAMA",
      "relevance_score": 0.6833333333333333
    }
  ]
}